pytropd/TropD_Example_Calculations.py
pytropd/__init__.py
pytropd/functions.py
pytropd/metrics.py
pytropd/pygeode_metrics.py
pytropd/pygtest.py
pytropd/tutorial.py
pytropd/xarray_metrics.py
pytropd/xrtest.py
pytropd-2.12.dist-info/LICENSE
pytropd-2.12.dist-info/METADATA
pytropd-2.12.dist-info/WHEEL
pytropd-2.12.dist-info/top_level.txt
pytropd-2.12.dist-info/RECORD
