Metadata-Version: 2.1
Name: pytropd
Version: 2.12
Summary: Calculation of metrics of tropical width
Home-page: https://tropd.github.io/pytropd/index.html
Author: Alison Ming, Paul William Staten, Samuel Smith
Author-email: admg26@gmail.com
License: GPL-3
Classifier: Programming Language :: Python :: 3
Requires: numpy
Requires: matplotlib
Requires: scipy
Requires-Python: >=3.8
License-File: LICENSE
Requires-Dist: numpy (>=1.19)
Requires-Dist: scipy (>=1.5)
